github_actions_utils/__init__.py
github_actions_utils/log_utils.py
tests/__init__.py
tests/test_github_group.py
github_actions_utils-1.0.1.dist-info/LICENSE
github_actions_utils-1.0.1.dist-info/METADATA
github_actions_utils-1.0.1.dist-info/WHEEL
github_actions_utils-1.0.1.dist-info/top_level.txt
github_actions_utils-1.0.1.dist-info/RECORD
